pt_datasets/__init__.py
pt_datasets/create_dataloader.py
pt_datasets/create_dataset.py
pt_datasets/datasets/AGNews.py
pt_datasets/datasets/COVID19Dataset.py
pt_datasets/datasets/Diabetes.py
pt_datasets/datasets/IMDB.py
pt_datasets/datasets/MalImg.py
pt_datasets/datasets/TwentyNewsgroups.py
pt_datasets/datasets/WDBC.py
pt_datasets/datasets/Yelp.py
pt_datasets/datasets/__init__.py
pt_datasets/download_covid_dataset.py
pt_datasets/encode_features.py
pt_datasets/life.py
pt_datasets/load_dataset.py
pt_datasets/text.py
pt_datasets/utils.py
pt_datasets/vision.py
pt_datasets-0.20.15.dist-info/LICENSE
pt_datasets-0.20.15.dist-info/METADATA
pt_datasets-0.20.15.dist-info/WHEEL
pt_datasets-0.20.15.dist-info/RECORD
