Metadata-Version: 2.1
Name: pt-datasets
Version: 0.20.15
Summary: Library for loading PyTorch datasets and data loaders.
License: AGPL-3.0 License
Author: Abien Fred Agarap
Author-email: abienfred.agarap@gmail.com
Requires-Python: >=3.11,<4.0
Classifier: License :: Other/Proprietary License
Classifier: Programming Language :: Python :: 3
Classifier: Programming Language :: Python :: 3.11
Classifier: Programming Language :: Python :: 3.12
Requires-Dist: gdown (>=5.1.0,<6.0.0)
Requires-Dist: imbalanced-learn (>=0.11.0,<0.12.0)
Requires-Dist: nltk (>=3.8.1,<4.0.0)
Requires-Dist: numba (>=0.58.1,<0.59.0)
Requires-Dist: numpy (<2.0)
Requires-Dist: opencv-python (>=4.7.0.72,<5.0.0.0)
Requires-Dist: opentsne (>=1.0.0,<2.0.0)
Requires-Dist: pymagnitude-lite (>=0.1.143,<0.2.0)
Requires-Dist: scikit-learn (>=1.2.2,<2.0.0)
Requires-Dist: spacy (>=3.7.4,<4.0.0)
Requires-Dist: torch (>=2.2.1,<3.0.0)
Requires-Dist: torchvision (>=0.17.1,<0.18.0)
Requires-Dist: umap-learn (>=0.5.3,<0.6.0)
